{"/guides/v2.1/mrg/ce/Sales/description.html":"https://dshevtsov.github.io/devdocs-archive/2.1/guides/v2.1/mrg/ce/Sales.html","/guides/v2.1/mrg/ce/Sales/dependencies.html":"https://dshevtsov.github.io/devdocs-archive/2.1/guides/v2.1/mrg/ce/Sales.html","/guides/v2.1/mrg/ce/Sales/services.html":"https://dshevtsov.github.io/devdocs-archive/2.1/guides/v2.1/mrg/ce/Sales.html","/guides/v2.1/contributor-guide/basic_template.html":"https://dshevtsov.github.io/devdocs-archive/2.1/guides/v2.1/contributor-guide/templates/basic_template.html","/guides/v2.1/howdoi/howdoi_template.html":"https://dshevtsov.github.io/devdocs-archive/2.1/guides/v2.1/contributor-guide/templates/basic_template.html","/guides/v2.1/cloud/before/before-setup-env-keys.html":"https://dshevtsov.github.io/devdocs-archive/2.1/guides/v2.1/cloud/before/before-setup-env-2_clone.html","/guides/v2.1/cloud/before/before-setup-env-env.html":"https://dshevtsov.github.io/devdocs-archive/2.1/guides/v2.1/cloud/before/before-setup-env-2_clone.html","/guides/v2.1/cloud/before/before-setup-env-perms.html":"https://dshevtsov.github.io/devdocs-archive/2.1/guides/v2.1/cloud/before/before-setup-env-install.html","/guides/v2.1/cloud/before/before-workspace-php.html":"https://dshevtsov.github.io/devdocs-archive/2.1/guides/v2.1/cloud/before/before-workspace-magento-prereqs.html","/guides/v2.1/cloud/before/before-workspace-cli.html":"https://dshevtsov.github.io/devdocs-archive/2.1/guides/v2.1/cloud/before/before-workspace-magento-prereqs.html","/guides/v2.1/cloud/before/before-setup-env-1_get-start.html":"https://dshevtsov.github.io/devdocs-archive/2.1/guides/v2.1/cloud/before/before-workspace-ssh.html","/guides/v2.1/cloud/access-acct/set-up-env.html":"https://dshevtsov.github.io/devdocs-archive/2.1/guides/v2.1/cloud/before/before-workspace.html","/guides/v2.1/cloud/access-acct/first-time-setup_template.html":"https://dshevtsov.github.io/devdocs-archive/2.1/guides/v2.1/cloud/before/before-workspace.html","/guides/v2.1/mktpl-quickstart/bk-marketplace-qs.html":"https://dshevtsov.github.io/devdocs-archive/2.1/guides/v2.1/extension-dev-guide/bk-extension-dev-guide.html","/guides/v2.1/mktpl-quickstart/intro-moreinfo.html":"https://dshevtsov.github.io/devdocs-archive/2.1/guides/v2.1/extension-dev-guide/bk-extension-dev-guide.html","/guides/v2.1/install-gde/continue.html":"https://dshevtsov.github.io/devdocs-archive/2.1/guides/v2.1/install-gde/bk-install-guide.html","/guides/v2.1/release-notes/2.3.0-install.html":"https://dshevtsov.github.io/devdocs-archive/2.1/guides/v2.1/release-notes/bk-release-notes.html","/guides/v2.1/ui-components/ui-component.html":"https://dshevtsov.github.io/devdocs-archive/2.1/guides/v2.1/ui_comp_guide/bk-ui_comps.html","/guides/v2.1/ui-components/ui-definition.html":"https://dshevtsov.github.io/devdocs-archive/2.1/guides/v2.1/ui_comp_guide/bk-ui_comps.html","/guides/v2.1/ui-components/ui-secondary.html":"https://dshevtsov.github.io/devdocs-archive/2.1/guides/v2.1/ui_comp_guide/bk-ui_comps.html","/guides/v2.1/ui-components/ui_components_js.html":"https://dshevtsov.github.io/devdocs-archive/2.1/guides/v2.1/ui_comp_guide/bk-ui_comps.html","/guides/v2.1/ui-components/ui-listing-grid.html":"https://dshevtsov.github.io/devdocs-archive/2.1/guides/v2.1/ui_comp_guide/bk-ui_comps.html","/guides/v2.1/ui_comp_guide/concepts/ui_comp_architecture_concept.html":"https://dshevtsov.github.io/devdocs-archive/2.1/guides/v2.1/ui_comp_guide/bk-ui_comps.html","/guides/v2.1/ui_comp_guide/ui_component_explained.html":"https://dshevtsov.github.io/devdocs-archive/2.1/guides/v2.1/ui_comp_guide/bk-ui_comps.html","/guides/v2.1/config-guide/cache/caching_low-level.html":"https://dshevtsov.github.io/devdocs-archive/2.1/guides/v2.1/config-guide/cache/cache-options.html","/guides/v2.1/config-guide/config/caching_frontend-cache-types.html":"https://dshevtsov.github.io/devdocs-archive/2.1/guides/v2.1/config-guide/cache/cache-types.html","/guides/v2.1/cloud/cli-ref/cli-ref-topic.html":"https://dshevtsov.github.io/devdocs-archive/2.1/guides/v2.1/cloud/reference/cli-ref-topic.html","/guides/v2.1/cloud/cloud-composer.html":"https://dshevtsov.github.io/devdocs-archive/2.1/guides/v2.1/cloud/reference/cloud-composer.html","/guides/v2.1/cloud/configure/fastly-vcl-extend-timeout.html":"https://dshevtsov.github.io/devdocs-archive/2.1/guides/v2.1/cloud/cdn/configure-fastly.html","/guides/v2.1/cloud/access-acct/fastly.html":"https://dshevtsov.github.io/devdocs-archive/2.1/guides/v2.1/cloud/cdn/configure-fastly.html","/guides/v2.1/cloud/basic-information/cloud-fastly.html":"https://dshevtsov.github.io/devdocs-archive/2.1/guides/v2.1/cloud/cdn/cloud-fastly.html","/guides/v2.1/cloud/release-notes/CloudReleaseNotes.html":"https://dshevtsov.github.io/devdocs-archive/2.1/guides/v2.1/cloud/release-notes/cloud-tools.html","/guides/v2.1/cloud/configure/cloud-vcl-custom-snippets.html":"https://dshevtsov.github.io/devdocs-archive/2.1/guides/v2.1/cloud/cdn/cloud-vcl-custom-snippets.html","/guides/v2.1/architecture/back-compatibility.html":"https://dshevtsov.github.io/devdocs-archive/2.1/guides/v2.1/extension-dev-guide/versioning/codebase-changes.html","/guides/v2.1/extension-dev-guide/backward-compatibility.html":"https://dshevtsov.github.io/devdocs-archive/2.1/guides/v2.1/extension-dev-guide/versioning/dependencies.html","/guides/v2.1/comp-mgr/compman-start.html":"https://dshevtsov.github.io/devdocs-archive/2.1/guides/v2.1/comp-mgr/module-man/compman-start.html","/guides/v2.1/install-gde/prereq/integrator_install.html":"https://dshevtsov.github.io/devdocs-archive/2.1/guides/v2.1/install-gde/composer.html","/guides/v2.1/install-gde/prereq/integrator_install_composer.html":"https://dshevtsov.github.io/devdocs-archive/2.1/guides/v2.1/install-gde/composer.html","/guides/v2.1/install-gde/prereq/integrator_install_ce.html":"https://dshevtsov.github.io/devdocs-archive/2.1/guides/v2.1/install-gde/composer.html","/guides/v2.1/install-gde/prereq/integrator_install_ee.html":"https://dshevtsov.github.io/devdocs-archive/2.1/guides/v2.1/install-gde/composer.html","/guides/v2.1/contributor-guide/contributing_docs_suggested.html":"https://dshevtsov.github.io/devdocs-archive/2.1/guides/v2.1/contributor-guide/contributing_docs_suggested.html","/guides/v2.1/howdoi/bk-how-do-i.html":"https://dshevtsov.github.io/devdocs-archive/2.1/guides/v2.1/contributor-guide/contributing_docs_suggested.html","/guides/v2.1/contributor-guide/quarterly-contributors.html":"https://dshevtsov.github.io/devdocs-archive/2.1/guides/v2.1/contributor-guide/contributors.html","/guides/v2.1/config-guide/cache/caching-cache-type.html":"https://dshevtsov.github.io/devdocs-archive/2.1/guides/v2.1/extension-dev-guide/cache/partial-caching/create-cache-type.html","/guides/v2.1/config-guide/database/database.html":"https://dshevtsov.github.io/devdocs-archive/2.1/guides/v2.1/extension-dev-guide/cache/partial-caching/database-caching.html","/guides/v2.1/mktpl-quickstart/dev-modtypes.html":"https://dshevtsov.github.io/devdocs-archive/2.1/guides/v2.1/extension-dev-guide/prepare/dev-modtypes.html","/guides/v2.1/mktpl-quickstart/dev-summary.html":"https://dshevtsov.github.io/devdocs-archive/2.1/guides/v2.1/extension-dev-guide/prepare/dev-summary.html","/guides/v2.1/mktpl-quickstart/dev-intro.html":"https://dshevtsov.github.io/devdocs-archive/2.1/guides/v2.1/extension-dev-guide/prepare/dev-summary.html","/guides/v2.1/install-gde/install/dev_updater.html":"https://dshevtsov.github.io/devdocs-archive/2.1/guides/v2.1/install-gde/install/cli/dev_options.html","/guides/v2.1/cloud/reference/docker-config.html":"https://dshevtsov.github.io/devdocs-archive/2.1/guides/v2.1/cloud/docker/docker-config.html","/guides/v2.1/cloud/composer-packages/ece-tools.html":"https://dshevtsov.github.io/devdocs-archive/2.1/guides/v2.1/cloud/project/ece-tools-update.html","/guides/v2.1/cloud/composer-packages/ece-tools-update.html":"https://dshevtsov.github.io/devdocs-archive/2.1/guides/v2.1/cloud/project/ece-tools-update.html","/guides/v2.1/cloud/before/integration-ip-addr.html":"https://dshevtsov.github.io/devdocs-archive/2.1/guides/v2.1/cloud/env/environments-start.html","/guides/v2.1/cloud/env/environment-tutorial-env-merge.html":"https://dshevtsov.github.io/devdocs-archive/2.1/guides/v2.1/cloud/env/environments-start.html","/guides/v2.1/cloud/deploy/configure-deploy.html":"https://dshevtsov.github.io/devdocs-archive/2.1/guides/v2.1/cloud/env/environments.html","/guides/v2.1/cloud/configure/fastly-vcl-badreferer.html":"https://dshevtsov.github.io/devdocs-archive/2.1/guides/v2.1/cloud/cdn/fastly-vcl-badreferer.html","/guides/v2.1/cloud/configure/fastly-vcl-blacklist.html":"https://dshevtsov.github.io/devdocs-archive/2.1/guides/v2.1/cloud/cdn/fastly-vcl-blacklist.html","/guides/v2.1/cloud/configure/fastly-vcl-whitelist.html":"https://dshevtsov.github.io/devdocs-archive/2.1/guides/v2.1/cloud/cdn/fastly-vcl-whitelist.html","/guides/v2.1/cloud/configure/fastly-vcl-wordpress.html":"https://dshevtsov.github.io/devdocs-archive/2.1/guides/v2.1/cloud/cdn/fastly-vcl-wordpress.html","/guides/v2.1/install-gde/prereq/apache-user.html":"https://dshevtsov.github.io/devdocs-archive/2.1/guides/v2.1/install-gde/prereq/file-sys-perms-over.html","/guides/v2.1/cloud/access-acct/first-time-deploy.html":"https://dshevtsov.github.io/devdocs-archive/2.1/guides/v2.1/cloud/setup/first-time-deploy.html","/guides/v2.1/cloud/access-acct/first-time-setup_import-prereq.html":"https://dshevtsov.github.io/devdocs-archive/2.1/guides/v2.1/cloud/setup/first-time-setup-import-first-steps.html","/guides/v2.1/cloud/access-acct/first-time-setup_import-first-steps.html":"https://dshevtsov.github.io/devdocs-archive/2.1/guides/v2.1/cloud/setup/first-time-setup-import-first-steps.html","/guides/v2.1/cloud/access-acct/first-time-setup_import-import.html":"https://dshevtsov.github.io/devdocs-archive/2.1/guides/v2.1/cloud/setup/first-time-setup-import-import.html","/guides/v2.1/cloud/access-acct/first-time-setup_import-prepare.html":"https://dshevtsov.github.io/devdocs-archive/2.1/guides/v2.1/cloud/setup/first-time-setup-import-prepare.html","/guides/v2.1/cloud/before/before-setup-env-overview.html":"https://dshevtsov.github.io/devdocs-archive/2.1/guides/v2.1/cloud/setup/first-time-setup.html","/guides/v2.1/cloud/howtos/environment-tutorial-set-mage-vars.html":"https://dshevtsov.github.io/devdocs-archive/2.1/guides/v2.1/cloud/setup/first-time-setup.html","/guides/v2.1/cloud/env/environment-tutorial-set-mage-vars.html":"https://dshevtsov.github.io/devdocs-archive/2.1/guides/v2.1/cloud/setup/first-time-setup.html","/guides/v2.1/cloud/access-acct/admin-env-vars.html":"https://dshevtsov.github.io/devdocs-archive/2.1/guides/v2.1/cloud/setup/first-time-setup.html","/guides/v2.1/cloud/access-acct/first-time-setup.html":"https://dshevtsov.github.io/devdocs-archive/2.1/guides/v2.1/cloud/setup/first-time-setup.html","/guides/v2.1/architecture/storefront_customization.html":"https://dshevtsov.github.io/devdocs-archive/2.1/guides/v2.1/architecture/frontend_custom_strategies.html","/guides/v2.1/cloud/project/admin-git-push.html":"https://dshevtsov.github.io/devdocs-archive/2.1/guides/v2.1/cloud/reference/git-integration.html","/guides/v2.1/":"https://dshevtsov.github.io/devdocs-archive/2.1/","/guides/v2.1/comp-mgr/install-extensions.html":"https://dshevtsov.github.io/devdocs-archive/2.1/extensions/install/","/guides/v2.1/architecture/versioning.html":"https://dshevtsov.github.io/devdocs-archive/2.1/guides/v2.1/extension-dev-guide/versioning/","/guides/v2.1/cloud/howtos/update-components.html":"https://dshevtsov.github.io/devdocs-archive/2.1/guides/v2.1/cloud/howtos/install-components.html","/guides/v2.1/test/integration/integration_test_setup.html":"https://dshevtsov.github.io/devdocs-archive/2.1/guides/v2.1/test/integration/integration_test_execution.html","/guides/v2.1/test/integration/integration_test_execution_cli.html":"https://dshevtsov.github.io/devdocs-archive/2.1/guides/v2.1/test/integration/integration_test_execution.html","/guides/v2.1/test/integration/integration_test_execution_phpstorm.html":"https://dshevtsov.github.io/devdocs-archive/2.1/guides/v2.1/test/integration/integration_test_execution.html","/guides/v2.1/mktpl-quickstart/intro-composer-gloss.html":"https://dshevtsov.github.io/devdocs-archive/2.1/guides/v2.1/extension-dev-guide/intro/intro-composer-gloss.html","/guides/v2.1/mktpl-quickstart/intro-composer.html":"https://dshevtsov.github.io/devdocs-archive/2.1/guides/v2.1/extension-dev-guide/intro/intro-composer.html","/guides/v2.1/extension-dev-guide/test/test_js-unit.html":"https://dshevtsov.github.io/devdocs-archive/2.1/guides/v2.1/test/js/jasmine.html","/guides/v2.1/contributor-guide/devdocs-maintainers.html":"https://dshevtsov.github.io/devdocs-archive/2.1/guides/v2.1/contributor-guide/maintainers.html","/guides/v2.1/config-guide/bootstrap/mage-run.html":"https://dshevtsov.github.io/devdocs-archive/2.1/guides/v2.1/config-guide/multi-site/ms_over.html","/guides/v2.1/cloud/before/before-project-owner.html":"https://dshevtsov.github.io/devdocs-archive/2.1/guides/v2.1/cloud/onboarding/onboarding-tasks.html","/guides/v2.1/get-started/order-tutorial/order-add-items.html":"https://dshevtsov.github.io/devdocs-archive/2.1/guides/v2.1/rest/tutorials/orders/order-add-items.html","/guides/v2.1/get-started/order-tutorial/order-admin-token.html":"https://dshevtsov.github.io/devdocs-archive/2.1/guides/v2.1/rest/tutorials/orders/order-admin-token.html","/guides/v2.1/get-started/order-tutorial/order-config-store.html":"https://dshevtsov.github.io/devdocs-archive/2.1/guides/v2.1/rest/tutorials/orders/order-config-store.html","/guides/v2.1/get-started/order-tutorial/order-create-customer.html":"https://dshevtsov.github.io/devdocs-archive/2.1/guides/v2.1/rest/tutorials/orders/order-create-customer.html","/guides/v2.1/get-started/order-tutorial/order-create-invoice.html":"https://dshevtsov.github.io/devdocs-archive/2.1/guides/v2.1/rest/tutorials/orders/order-create-invoice.html","/guides/v2.1/get-started/order-tutorial/order-create-order.html":"https://dshevtsov.github.io/devdocs-archive/2.1/guides/v2.1/rest/tutorials/orders/order-create-order.html","/guides/v2.1/get-started/order-tutorial/order-create-quote.html":"https://dshevtsov.github.io/devdocs-archive/2.1/guides/v2.1/rest/tutorials/orders/order-create-quote.html","/guides/v2.1/get-started/order-tutorial/order-create-shipment.html":"https://dshevtsov.github.io/devdocs-archive/2.1/guides/v2.1/rest/tutorials/orders/order-create-shipment.html","/guides/v2.1/get-started/order-tutorial/order-intro.html":"https://dshevtsov.github.io/devdocs-archive/2.1/guides/v2.1/rest/tutorials/orders/order-intro.html","/guides/v2.1/get-started/order-tutorial/order-issue-refund.html":"https://dshevtsov.github.io/devdocs-archive/2.1/guides/v2.1/rest/tutorials/orders/order-issue-refund.html","/guides/v2.1/get-started/order-tutorial/order-prepare-checkout.html":"https://dshevtsov.github.io/devdocs-archive/2.1/guides/v2.1/rest/tutorials/orders/order-prepare-checkout.html","/guides/v2.1/config-guide/cache/cache-priv-over.html":"https://dshevtsov.github.io/devdocs-archive/2.1/guides/v2.1/extension-dev-guide/cache/page-caching.html","/guides/v2.1/mktpl-quickstart/dev-filesys.html":"https://dshevtsov.github.io/devdocs-archive/2.1/guides/v2.1/extension-dev-guide/prepare/prepare_file-str.html","/guides/v2.1/config-guide/cache/cache-priv-priv.html":"https://dshevtsov.github.io/devdocs-archive/2.1/guides/v2.1/extension-dev-guide/cache/page-caching/public-content.html","/guides/v2.1/config-guide/cache/cache-priv-context.html":"https://dshevtsov.github.io/devdocs-archive/2.1/guides/v2.1/extension-dev-guide/cache/page-caching/public-content.html","/guides/v2.1/config-guide/cache/cache-priv-inval.html":"https://dshevtsov.github.io/devdocs-archive/2.1/guides/v2.1/extension-dev-guide/cache/page-caching/public-content.html","/guides/v2.1/cloud/discover-arch.html":"https://dshevtsov.github.io/devdocs-archive/2.1/guides/v2.1/cloud/architecture/pro-architecture.html","/guides/v2.1/cloud/reference/discover-arch.html":"https://dshevtsov.github.io/devdocs-archive/2.1/guides/v2.1/cloud/architecture/pro-architecture.html","/guides/v2.1/cloud/discover-workflow.html":"https://dshevtsov.github.io/devdocs-archive/2.1/guides/v2.1/cloud/architecture/pro-develop-deploy-workflow.html","/guides/v2.1/cloud/welcome/discover-workflow.html":"https://dshevtsov.github.io/devdocs-archive/2.1/guides/v2.1/cloud/architecture/pro-develop-deploy-workflow.html","/guides/v2.1/cloud/before/before-setup-env-cron.html":"https://dshevtsov.github.io/devdocs-archive/2.1/guides/v2.1/cloud/project/project-conf-files_magento-app.html","/guides/v2.1/cloud/howtos/upgrade-magento.html":"https://dshevtsov.github.io/devdocs-archive/2.1/guides/v2.1/cloud/project/project-upgrade.html","/guides/v2.1/cloud/project/project-priv-repos.html":"https://dshevtsov.github.io/devdocs-archive/2.1/guides/v2.1/cloud/project/project-webint-branch.html","/guides/v2.1/cloud/admin/admin-snap.html":"https://dshevtsov.github.io/devdocs-archive/2.1/guides/v2.1/cloud/project/project-webint-snap.html","/guides/v2.1/cloud/admin/administer.html":"https://dshevtsov.github.io/devdocs-archive/2.1/guides/v2.1/cloud/project/projects.html","/guides/v2.1/release-notes/backward-incompatible-changes/commerce.html":"https://dshevtsov.github.io/devdocs-archive/2.1/guides/v2.1/release-notes/backward-incompatible-changes/reference.html","/guides/v2.1/release-notes/backward-incompatible-changes/open-source.html":"https://dshevtsov.github.io/devdocs-archive/2.1/guides/v2.1/release-notes/backward-incompatible-changes/reference.html","/ui_comp_guide/concepts/ui_comp_requirejs_concept.md":"https://dshevtsov.github.io/devdocs-archive/2.1/guides/v2.1/javascript-dev-guide/javascript/requirejs_concept.html","/community/resources/index.html":"https://dshevtsov.github.io/devdocs-archive/2.1/community/resources/resources.html","/guides/v2.1/frontend-dev-guide/css-topics/css-breakpoints.html":"https://dshevtsov.github.io/devdocs-archive/2.1/guides/v2.1/frontend-dev-guide/responsive-web-design/rwd-breakpoints.html","/guides/v2.1/cloud/env/smart-wizards.html":"https://dshevtsov.github.io/devdocs-archive/2.1/guides/v2.1/cloud/deploy/smart-wizards.html","/guides/v2.1/cloud/live/stage-prod-over.html":"https://dshevtsov.github.io/devdocs-archive/2.1/guides/v2.1/cloud/live/stage-prod-live.html","/guides/v2.1/install-gde/system-requirements-2.1-tech.html":"https://dshevtsov.github.io/devdocs-archive/2.1/guides/v2.1/install-gde/system-requirements-tech.html","/guides/v2.1/install-gde/system-requirements-2.1.html":"https://dshevtsov.github.io/devdocs-archive/2.1/guides/v2.1/install-gde/system-requirements.html","/magento-system-requirements.html":"https://dshevtsov.github.io/devdocs-archive/2.1/guides/v2.1/install-gde/system-requirements.html","/guides/v2.1/install-gde/system-requirements-tls-parent.html":"https://dshevtsov.github.io/devdocs-archive/2.1/guides/v2.1/install-gde/system-requirements_repo-tls1-2.html","/guides/v2.1/coding-standards/technical-guidelines/technical-guidelines.html":"https://dshevtsov.github.io/devdocs-archive/2.1/guides/v2.1/coding-standards/technical-guidelines.html","/guides/v2.1/mktpl-quickstart/dev-test.html":"https://dshevtsov.github.io/devdocs-archive/2.1/guides/v2.1/extension-dev-guide/validate/test-module.html","/guides/v2.1/cloud/trouble/trouble_fastly.html":"https://dshevtsov.github.io/devdocs-archive/2.1/guides/v2.1/cloud/cdn/trouble-fastly.html","/guides/v2.1/config-guide/varnish/config-use-varnish.html":"https://dshevtsov.github.io/devdocs-archive/2.1/guides/v2.1/config-guide/varnish/use-varnish-cache.html","/guides/v2.1/cloud/admin/admin-user-admin.html":"https://dshevtsov.github.io/devdocs-archive/2.1/guides/v2.1/cloud/project/user-admin.html","/guides/v2.1/cloud/env/environment-vars_cloud.html":"https://dshevtsov.github.io/devdocs-archive/2.1/guides/v2.1/cloud/env/variables-cloud.html","/guides/v2.1/magento-devdocs-whatsnew.html":"https://dshevtsov.github.io/devdocs-archive/2.1/whats-new.html","/guides/v2.1/extension-dev-guide/security/writing-secure-code.html":"https://dshevtsov.github.io/devdocs-archive/2.1/guides/v2.1/ext-best-practices/security/writing-secure-code.html"}